{
  "productos": [
    {
      "nombre": "Tabletas clasica",
      "precio": "$220",
      "link": "#",
      "tamano": "clasica"
    },
    {
      "nombre": "Tabletas evento",
      "precio": "$22010",
      "link": "#",
      "tamano": "evento"
    },
    {
      "nombre": "Caja de 9 Mendians",
      "precio": "$450",
      "link": "#",
      "tamano": "Mendians"
    },
    {
      "nombre": "Tabletas 60% Cacao",
      "precio": "$190",
      "link": "#",
      "tamano": "4"
    },
    {
      "nombre": "Tableta Dubai",
      "precio": "$300",
      "link": "#",
      "tamano": "dubai"
    },
    {
      "nombre": "Tab. crema de Avellanas",
      "precio": "$300",
      "link": "#",
      "tamano": "5"
    },
    {
      "nombre": "Caja de 6 Bombones",
      "precio": "$390",
      "tamano": "6",
      "link": "index.html#configurador"
    },
    {
      "nombre": "Tab. Franui",
      "precio": "$300",
      "link": "#",
      "tamano": "9"
    },
    {
      "nombre": "Caja de 12 Bombones",
      "precio": "$690",
      "tamano": "12",
      "link": "index.html#configurador"
    },
    {
      "nombre": "Tab. Dulce de leche y oreos",
      "precio": "$300",
      "link": "#",
      "tamano": "7"
    },
    {
      "nombre": "Caja de 24 Bombones",
      "precio": "$6000",
      "tamano": "24",
      "link": "index.html#configurador"
    }
  ]
}